{
  "gold.ua_user_lifetime_activity_daily": {
    "_model": "gold__ua_user_lifetime_activity_daily.sql",
    "_sources": ["silver__user_activity_daily", "silver__inapp_table", "silver__subscription_table", "silver__applovin_ad_user_daily", "silver__users_scd2"],
    "_join_strategy": "4 CTEs (activity/inapp/subscription/ad_revenue) are enriched via LEFT ASOF JOIN on silver.users_scd2 (install_time <= event_time), then UNION ALL and re-aggregated. Final INNER JOIN back to user_lifetimes for dimension columns.",
    "cohort_date": {"source": "silver.users_scd2", "formula": "toDate(install_time)", "via_cte": "user_lifetimes"},
    "cohort_month": {"source": "silver.users_scd2", "formula": "toStartOfMonth(toDate(install_time))", "via_cte": "user_lifetimes"},
    "cohort_week": {"source": "silver.users_scd2", "formula": "toStartOfWeek(toDate(install_time), 5)", "via_cte": "user_lifetimes"},
    "event_date": {"source": "silver.user_activity_daily / silver.inapp_table / silver.subscription_table / silver.applovin_ad_user_daily", "formula": "activity_date_utc or toDate(event_time) or event_date depending on CTE", "via_cte": "aggregated"},
    "day_idx": {"source": "computed", "formula": "toUInt16(dateDiff('day', cohort_date, event_date))", "via_cte": "final SELECT"},
    "platform": {"source": "silver.users_scd2", "formula": "multiIf(platform LIKE '%ios%', 'ios', platform LIKE '%and%', 'android', 'unknown')", "via_cte": "user_lifetimes"},
    "application": {"source": "silver.users_scd2", "formula": "coalesce(nullIf(app_name, ''), 'unknown')", "via_cte": "user_lifetimes"},
    "country": {"source": "silver.users_scd2", "formula": "coalesce(country_code, '')", "via_cte": "user_lifetimes"},
    "media_source": {"source": "silver.users_scd2", "formula": "coalesce(media_source, '')", "via_cte": "user_lifetimes"},
    "promo_campaign": {"source": "silver.users_scd2", "formula": "coalesce(promo_campaign, '')", "via_cte": "user_lifetimes"},
    "promo_campaign_id": {"source": "silver.users_scd2", "formula": "coalesce(promo_campaign_id, '')", "via_cte": "user_lifetimes"},
    "ad": {"source": "silver.users_scd2", "formula": "coalesce(ad, '')", "via_cte": "user_lifetimes"},
    "adset": {"source": "silver.users_scd2", "formula": "coalesce(adset, '')", "via_cte": "user_lifetimes"},
    "install_device_name": {"source": "silver.users_scd2", "formula": "coalesce(install_device_name, '')", "via_cte": "user_lifetimes"},
    "install_device_type": {"source": "silver.users_scd2", "formula": "coalesce(install_device_type, '')", "via_cte": "user_lifetimes"},
    "client_id": {"source": "silver.users_scd2", "formula": "pass-through", "via_cte": "user_lifetimes"},
    "user_lifetime_id": {"source": "silver.users_scd2", "formula": "pass-through", "via_cte": "user_lifetimes"},
    "user_lifetime_number": {"source": "silver.users_scd2", "formula": "pass-through", "via_cte": "user_lifetimes"},
    "install_time": {"source": "silver.users_scd2", "formula": "pass-through", "via_cte": "user_lifetimes"},
    "lifetime_start_date": {"source": "silver.users_scd2", "formula": "toDate(install_time)", "via_cte": "user_lifetimes"},
    "lifetime_end_date": {"source": "silver.users_scd2", "formula": "if(isNull(lifetime_end_time), NULL, toDate(lifetime_end_time))", "via_cte": "user_lifetimes"},
    "sessions_count": {"source": "silver.user_activity_daily", "formula": "sum(sessions_count)", "via_cte": "activity_daily -> aggregated", "aggregation": "SUM across UNION ALL of 4 CTEs, GROUP BY (event_date, application, client_id, user_lifetime_id)"},
    "session_duration_seconds_total": {"source": "silver.user_activity_daily", "formula": "sum(session_duration_seconds_total)", "via_cte": "activity_daily -> aggregated", "aggregation": "SUM"},
    "session_event_count_total": {"source": "silver.user_activity_daily", "formula": "sum(session_event_count_total)", "via_cte": "activity_daily -> aggregated", "aggregation": "SUM"},
    "app_version_last": {"source": "silver.user_activity_daily", "formula": "argMax(app_version_last, app_version_priority)", "via_cte": "activity_daily -> aggregated", "aggregation": "argMax (picks activity CTE value over others)"},
    "purchases": {"source": "silver.inapp_table + silver.subscription_table", "formula": "sum(countIf(event_name='purchase')) from inapp + countIf(event_name='purchase' AND period_type='normal') from subs", "via_cte": "inapp_daily + subscription_daily -> aggregated", "aggregation": "SUM"},
    "refunds": {"source": "silver.inapp_table + silver.subscription_table", "formula": "sum(countIf(event_name='refund'))", "via_cte": "inapp_daily + subscription_daily -> aggregated", "aggregation": "SUM"},
    "inapp_purchases": {"source": "silver.inapp_table", "formula": "countIf(event_name='purchase')", "via_cte": "inapp_daily -> aggregated", "aggregation": "SUM"},
    "inapp_refunds_num": {"source": "silver.inapp_table", "formula": "countIf(event_name='refund')", "via_cte": "inapp_daily -> aggregated", "aggregation": "SUM"},
    "subscription_purchases": {"source": "silver.subscription_table", "formula": "countIf(event_name='purchase' AND period_type='normal')", "via_cte": "subscription_daily -> aggregated", "aggregation": "SUM"},
    "subscription_refunds_num": {"source": "silver.subscription_table", "formula": "countIf(event_name='refund')", "via_cte": "subscription_daily -> aggregated", "aggregation": "SUM"},
    "trial_purchases": {"source": "silver.subscription_table", "formula": "countIf(event_name='purchase' AND period_type LIKE '%trial%')", "via_cte": "subscription_daily -> aggregated", "aggregation": "SUM"},
    "trial_converted_purchases": {"source": "silver.subscription_table", "formula": "countIf(event_name='purchase' AND is_trial_conversion=1)", "via_cte": "subscription_daily -> aggregated", "aggregation": "SUM"},
    "renewal_purchases": {"source": "silver.subscription_table", "formula": "countIf(event_name='purchase' AND type='RENEWAL')", "via_cte": "subscription_daily -> aggregated", "aggregation": "SUM"},
    "cancelations": {"source": "silver.subscription_table", "formula": "countIf(cancel_ind=1)", "via_cte": "subscription_daily -> aggregated", "aggregation": "SUM"},
    "ad_impressions": {"source": "silver.applovin_ad_user_daily", "formula": "sum(impressions_count)", "via_cte": "ad_revenue_daily -> aggregated", "aggregation": "SUM"},
    "ad_impressions_rewarded": {"source": "silver.applovin_ad_user_daily", "formula": "sum(impressions_rewarded)", "via_cte": "ad_revenue_daily -> aggregated", "aggregation": "SUM"},
    "ad_impressions_interstitial": {"source": "silver.applovin_ad_user_daily", "formula": "sum(impressions_interstitial)", "via_cte": "ad_revenue_daily -> aggregated", "aggregation": "SUM"},
    "ad_impressions_banner": {"source": "silver.applovin_ad_user_daily", "formula": "sum(impressions_banner)", "via_cte": "ad_revenue_daily -> aggregated", "aggregation": "SUM"},
    "inapp_revenue_gross": {"source": "silver.inapp_table", "formula": "sumIf(abs(price_gross), event_name='purchase')", "via_cte": "inapp_daily -> aggregated", "aggregation": "SUM. Price is net USD from silver.inapp_table (already converted via calc_price_usd macro)"},
    "subs_revenue_gross": {"source": "silver.subscription_table", "formula": "sumIf(abs(price_gross), event_name='purchase' AND period_type='normal')", "via_cte": "subscription_daily -> aggregated", "aggregation": "SUM"},
    "ad_revenue_gross": {"source": "silver.applovin_ad_user_daily", "formula": "sum(ad_revenue_total)", "via_cte": "ad_revenue_daily -> aggregated", "aggregation": "SUM"},
    "inapp_refunds_revenue_net": {"source": "silver.inapp_table", "formula": "sumIf(abs(price), event_name='refund')", "via_cte": "inapp_daily -> aggregated", "aggregation": "SUM"},
    "subs_refunds_revenue_net": {"source": "silver.subscription_table", "formula": "sumIf(abs(price), event_name='refund')", "via_cte": "subscription_daily -> aggregated", "aggregation": "SUM"},
    "inapp_revenue_net": {"source": "silver.inapp_table", "formula": "sumIf(if(event_name='purchase', 1, -1) * abs(price), event_name IN ('purchase','refund'))", "via_cte": "inapp_daily -> aggregated", "aggregation": "SUM. Purchases positive, refunds negative."},
    "subs_revenue_net": {"source": "silver.subscription_table", "formula": "sumIf(if(event_name='purchase', 1, -1) * abs(price), (event_name='purchase' AND period_type='normal') OR event_name='refund')", "via_cte": "subscription_daily -> aggregated", "aggregation": "SUM. Only normal-period purchases count, refunds subtract."},
    "ad_revenue_rewarded_gross": {"source": "silver.applovin_ad_user_daily", "formula": "sum(revenue_rewarded)", "via_cte": "ad_revenue_daily -> aggregated", "aggregation": "SUM"},
    "ad_revenue_interstitial_gross": {"source": "silver.applovin_ad_user_daily", "formula": "sum(revenue_interstitial)", "via_cte": "ad_revenue_daily -> aggregated", "aggregation": "SUM"},
    "ad_revenue_banner_gross": {"source": "silver.applovin_ad_user_daily", "formula": "sum(revenue_banner)", "via_cte": "ad_revenue_daily -> aggregated", "aggregation": "SUM"},
    "total_revenue_gross": {"source": "computed", "formula": "inapp_revenue_gross + subs_revenue_gross + ad_revenue_gross", "via_cte": "final SELECT"},
    "total_revenue_net": {"source": "computed", "formula": "inapp_revenue_net + subs_revenue_net + ad_revenue_gross", "via_cte": "final SELECT", "aggregation": "Note: uses ad_revenue_GROSS (no net concept for ads)"},
    "version": {"source": "system", "formula": "now()", "via_cte": "final SELECT"}
  },

  "gold.ua_cohort_users": {
    "_model": "gold__ua_cohort_users.sql",
    "_sources": ["silver__users_scd2"],
    "_join_strategy": "Direct SELECT from silver.users_scd2, no joins. Filters: install_date >= 2024-02-08, client_id not null/empty/zero-UUID.",
    "cohort_date": {"source": "silver.users_scd2", "formula": "toDate(install_date)"},
    "cohort_month": {"source": "silver.users_scd2", "formula": "toStartOfMonth(toDate(install_date))"},
    "cohort_week": {"source": "silver.users_scd2", "formula": "toStartOfWeek(toDate(install_date), 5)"},
    "platform": {"source": "silver.users_scd2", "formula": "multiIf(platform LIKE '%ios%', 'ios', LIKE '%and%', 'android', 'unknown')"},
    "application": {"source": "silver.users_scd2", "formula": "coalesce(nullIf(app_name, ''), 'unknown')"},
    "country": {"source": "silver.users_scd2", "formula": "coalesce(country_code, '')"},
    "media_source": {"source": "silver.users_scd2", "formula": "coalesce(media_source, '')"},
    "promo_campaign": {"source": "silver.users_scd2", "formula": "coalesce(promo_campaign, '')"},
    "promo_campaign_id": {"source": "silver.users_scd2", "formula": "coalesce(promo_campaign_id, '')"},
    "ad": {"source": "silver.users_scd2", "formula": "coalesce(ad, '')"},
    "adset": {"source": "silver.users_scd2", "formula": "coalesce(adset, '')"},
    "install_device_name": {"source": "silver.users_scd2", "formula": "coalesce(install_device_name, '')"},
    "install_device_type": {"source": "silver.users_scd2", "formula": "coalesce(install_device_type, '')"},
    "client_id": {"source": "silver.users_scd2", "formula": "pass-through"},
    "user_lifetime_id": {"source": "silver.users_scd2", "formula": "pass-through"},
    "user_lifetime_number": {"source": "silver.users_scd2", "formula": "pass-through"},
    "lifetime_start_date": {"source": "silver.users_scd2", "formula": "toDate(install_time)"},
    "lifetime_end_date": {"source": "silver.users_scd2", "formula": "if(isNull(lifetime_end_time), NULL, toDate(lifetime_end_time))"}
  },

  "gold.ua_payers": {
    "_model": "gold__ua_payers.sql",
    "_sources": ["gold__ua_cohort_users", "silver__inapp_table", "silver__subscription_table"],
    "_join_strategy": "UNION ALL of inapp purchases (event_name='purchase') and subscription purchases, then INNER JOIN to gold.ua_cohort_users to pin purchases to correct user lifetime window (event_date >= lifetime_start_date AND < lifetime_end_date). Aggregated per user lifetime.",
    "cohort_date": {"source": "gold.ua_cohort_users", "formula": "pass-through"},
    "cohort_month": {"source": "gold.ua_cohort_users", "formula": "pass-through"},
    "cohort_week": {"source": "gold.ua_cohort_users", "formula": "pass-through"},
    "platform": {"source": "gold.ua_cohort_users", "formula": "pass-through"},
    "application": {"source": "gold.ua_cohort_users", "formula": "pass-through"},
    "country": {"source": "gold.ua_cohort_users", "formula": "pass-through"},
    "media_source": {"source": "gold.ua_cohort_users", "formula": "pass-through"},
    "promo_campaign": {"source": "gold.ua_cohort_users", "formula": "pass-through"},
    "promo_campaign_id": {"source": "gold.ua_cohort_users", "formula": "pass-through"},
    "ad": {"source": "gold.ua_cohort_users", "formula": "pass-through"},
    "adset": {"source": "gold.ua_cohort_users", "formula": "pass-through"},
    "client_id": {"source": "gold.ua_cohort_users", "formula": "pass-through"},
    "user_lifetime_id": {"source": "gold.ua_cohort_users", "formula": "pass-through"},
    "is_inapp_payer": {"source": "silver.inapp_table", "formula": "toUInt8(inapp_purchases > 0)", "aggregation": "Flag derived from count"},
    "is_subscription_payer": {"source": "silver.subscription_table", "formula": "toUInt8(subscription_purchases > 0)", "aggregation": "Flag derived from count"},
    "purchases_total": {"source": "silver.inapp_table + silver.subscription_table", "formula": "count()", "aggregation": "COUNT of all purchases in lifetime window"},
    "inapp_purchases": {"source": "silver.inapp_table", "formula": "countIf(purchase_type='inapp')", "aggregation": "COUNT"},
    "subscription_purchases": {"source": "silver.subscription_table", "formula": "countIf(purchase_type='subscription')", "aggregation": "COUNT"},
    "inapp_currency": {"source": "silver.inapp_table", "formula": "if(countDistinct(currency)=1, any(currency), 'MULTI')"},
    "subscription_currency": {"source": "silver.subscription_table", "formula": "if(countDistinct(currency)=1, any(currency), 'MULTI')"},
    "inapp_amount_local_total": {"source": "silver.inapp_table", "formula": "if(single_currency, sumIf(local_amount, inapp), NULL)"},
    "subscription_amount_local_total": {"source": "silver.subscription_table", "formula": "if(single_currency, sumIf(local_amount, subscription), NULL)"},
    "inapp_amount_usd_total": {"source": "silver.inapp_table", "formula": "sumIf(amount_usd, purchase_type='inapp')", "aggregation": "SUM in USD"},
    "subscription_amount_usd_total": {"source": "silver.subscription_table", "formula": "sumIf(amount_usd, purchase_type='subscription')", "aggregation": "SUM in USD"},
    "first_purchase_timestamp": {"source": "silver.inapp_table + silver.subscription_table", "formula": "min(purchase_time)", "aggregation": "MIN across all purchase types"},
    "first_purchase_date": {"source": "computed", "formula": "toDate(min(purchase_time))"},
    "first_inapp_purchase_date": {"source": "silver.inapp_table", "formula": "minIf(event_date, purchase_type='inapp')"},
    "first_subscription_purchase_date": {"source": "silver.subscription_table", "formula": "minIf(event_date, purchase_type='subscription')"},
    "version": {"source": "system", "formula": "now()"}
  },

  "gold.ua_cohort_long": {
    "_model": "gold__ua_cohort_long.sql",
    "_sources": ["gold__ua_cohort_users", "silver__ua_costs", "gold__ua_user_lifetime_activity_daily"],
    "_join_strategy": "3 branches via UNION ALL: (1) installs from gold.ua_cohort_users on day_idx=0, (2) UA costs from silver.ua_costs on day_idx=0, (3) activity+monetization from gold.ua_user_lifetime_activity_daily. All unioned and SUM-aggregated per dimension group.",
    "cohort_date": {"source": "gold.ua_cohort_users / gold.ua_user_lifetime_activity_daily", "formula": "pass-through"},
    "cohort_month": {"source": "pass-through", "formula": "pass-through"},
    "cohort_week": {"source": "pass-through", "formula": "pass-through"},
    "event_date": {"source": "gold.ua_user_lifetime_activity_daily", "formula": "pass-through (cohort_date for day 0 branches)"},
    "day_idx": {"source": "gold.ua_user_lifetime_activity_daily", "formula": "pass-through (0 for install/cost branches)"},
    "platform": {"source": "pass-through", "formula": "pass-through"},
    "application": {"source": "pass-through", "formula": "pass-through"},
    "country": {"source": "pass-through", "formula": "pass-through"},
    "media_source": {"source": "pass-through", "formula": "pass-through"},
    "promo_campaign": {"source": "pass-through", "formula": "pass-through"},
    "promo_campaign_id": {"source": "pass-through", "formula": "pass-through"},
    "ad": {"source": "pass-through", "formula": "pass-through"},
    "adset": {"source": "pass-through", "formula": "pass-through"},
    "installs": {"source": "gold.ua_cohort_users", "formula": "sum(installs)", "aggregation": "SUM. Non-zero only from installs_day0 CTE: count() on day_idx=0"},
    "impressions": {"source": "silver.ua_costs", "formula": "sum(impressions)", "aggregation": "SUM. Non-zero only from costs_day0 CTE"},
    "clicks": {"source": "silver.ua_costs", "formula": "sum(clicks)", "aggregation": "SUM. Non-zero only from costs_day0 CTE"},
    "cost": {"source": "silver.ua_costs", "formula": "sum(cost)", "aggregation": "SUM. Non-zero only from costs_day0 CTE"},
    "clients_sdk": {"source": "gold.ua_user_lifetime_activity_daily", "formula": "sum(countIf(sessions_count > 0))", "aggregation": "SUM. Distinct users with at least 1 session, from activity_and_monetization CTE"},
    "purchases": {"source": "gold.ua_user_lifetime_activity_daily", "formula": "sum(purchases)", "aggregation": "SUM"},
    "refunds": {"source": "gold.ua_user_lifetime_activity_daily", "formula": "sum(refunds)", "aggregation": "SUM"},
    "inapp_purchases": {"source": "gold.ua_user_lifetime_activity_daily", "formula": "sum(inapp_purchases)", "aggregation": "SUM"},
    "inapp_refunds_num": {"source": "gold.ua_user_lifetime_activity_daily", "formula": "sum(inapp_refunds_num)", "aggregation": "SUM"},
    "subscription_purchases": {"source": "gold.ua_user_lifetime_activity_daily", "formula": "sum(subscription_purchases)", "aggregation": "SUM"},
    "subscription_refunds_num": {"source": "gold.ua_user_lifetime_activity_daily", "formula": "sum(subscription_refunds_num)", "aggregation": "SUM"},
    "trial_purchases": {"source": "gold.ua_user_lifetime_activity_daily", "formula": "sum(trial_purchases)", "aggregation": "SUM"},
    "trial_converted_purchases": {"source": "gold.ua_user_lifetime_activity_daily", "formula": "sum(trial_converted_purchases)", "aggregation": "SUM"},
    "renewal_purchases": {"source": "gold.ua_user_lifetime_activity_daily", "formula": "sum(renewal_purchases)", "aggregation": "SUM"},
    "cancelations": {"source": "gold.ua_user_lifetime_activity_daily", "formula": "sum(cancelations)", "aggregation": "SUM"},
    "ad_impressions": {"source": "gold.ua_user_lifetime_activity_daily", "formula": "sum(ad_impressions)", "aggregation": "SUM"},
    "ad_impressions_rewarded": {"source": "gold.ua_user_lifetime_activity_daily", "formula": "sum(ad_impressions_rewarded)", "aggregation": "SUM"},
    "ad_impressions_interstitial": {"source": "gold.ua_user_lifetime_activity_daily", "formula": "sum(ad_impressions_interstitial)", "aggregation": "SUM"},
    "ad_impressions_banner": {"source": "gold.ua_user_lifetime_activity_daily", "formula": "sum(ad_impressions_banner)", "aggregation": "SUM"},
    "inapp_revenue_gross": {"source": "gold.ua_user_lifetime_activity_daily", "formula": "sum(inapp_revenue_gross)", "aggregation": "SUM"},
    "subs_revenue_gross": {"source": "gold.ua_user_lifetime_activity_daily", "formula": "sum(subs_revenue_gross)", "aggregation": "SUM"},
    "ad_revenue_gross": {"source": "gold.ua_user_lifetime_activity_daily", "formula": "sum(ad_revenue_gross)", "aggregation": "SUM"},
    "inapp_refunds_revenue_net": {"source": "gold.ua_user_lifetime_activity_daily", "formula": "sum(inapp_refunds_revenue_net)", "aggregation": "SUM"},
    "subs_refunds_revenue_net": {"source": "gold.ua_user_lifetime_activity_daily", "formula": "sum(subs_refunds_revenue_net)", "aggregation": "SUM"},
    "inapp_revenue_net": {"source": "gold.ua_user_lifetime_activity_daily", "formula": "sum(inapp_revenue_net)", "aggregation": "SUM"},
    "subs_revenue_net": {"source": "gold.ua_user_lifetime_activity_daily", "formula": "sum(subs_revenue_net)", "aggregation": "SUM"},
    "ad_revenue_rewarded_gross": {"source": "gold.ua_user_lifetime_activity_daily", "formula": "sum(ad_revenue_rewarded_gross)", "aggregation": "SUM"},
    "ad_revenue_interstitial_gross": {"source": "gold.ua_user_lifetime_activity_daily", "formula": "sum(ad_revenue_interstitial_gross)", "aggregation": "SUM"},
    "ad_revenue_banner_gross": {"source": "gold.ua_user_lifetime_activity_daily", "formula": "sum(ad_revenue_banner_gross)", "aggregation": "SUM"},
    "total_revenue_gross": {"source": "computed", "formula": "inapp_revenue_gross + subs_revenue_gross + ad_revenue_gross"},
    "total_revenue_net": {"source": "computed", "formula": "inapp_revenue_net + subs_revenue_net + ad_revenue_gross", "aggregation": "Note: uses ad_revenue_GROSS (no net concept for ads)"},
    "version": {"source": "system", "formula": "now()"}
  },

  "gold.ua_cohort_activity_utn": {
    "_model": "gold__ua_cohort_activity_utn.sql",
    "_sources": ["gold__ua_user_lifetime_activity_daily"],
    "_join_strategy": "Direct SELECT from gold.ua_user_lifetime_activity_daily, GROUP BY all dimension columns. No joins.",
    "cohort_date": {"source": "gold.ua_user_lifetime_activity_daily", "formula": "pass-through"},
    "cohort_month": {"source": "gold.ua_user_lifetime_activity_daily", "formula": "pass-through"},
    "cohort_week": {"source": "gold.ua_user_lifetime_activity_daily", "formula": "pass-through"},
    "platform": {"source": "gold.ua_user_lifetime_activity_daily", "formula": "pass-through"},
    "application": {"source": "gold.ua_user_lifetime_activity_daily", "formula": "pass-through"},
    "country": {"source": "gold.ua_user_lifetime_activity_daily", "formula": "pass-through"},
    "media_source": {"source": "gold.ua_user_lifetime_activity_daily", "formula": "pass-through"},
    "promo_campaign": {"source": "gold.ua_user_lifetime_activity_daily", "formula": "pass-through"},
    "promo_campaign_id": {"source": "gold.ua_user_lifetime_activity_daily", "formula": "pass-through"},
    "ad": {"source": "gold.ua_user_lifetime_activity_daily", "formula": "pass-through"},
    "adset": {"source": "gold.ua_user_lifetime_activity_daily", "formula": "pass-through"},
    "clients_sdk_utn": {"source": "gold.ua_user_lifetime_activity_daily", "formula": "uniqExactIf(user_lifetime_id, sessions_count > 0)", "aggregation": "COUNT DISTINCT users with at least 1 session (unlimited time, no maturity guard)"},
    "version": {"source": "system", "formula": "now()"}
  },

  "gold.monetization_curves": {
    "_model": "gold__monetization_curves.sql",
    "_sources": ["gold__ua_cohort_long"],
    "_join_strategy": "Reads from gold.ua_cohort_long. Builds per-cohort arrays via sumMap, then explodes to one-row-per-day via arrayJoin(range(mature_day_max+1)). No joins.",
    "cohort_date": {"source": "gold.ua_cohort_long", "formula": "pass-through"},
    "cohort_month": {"source": "gold.ua_cohort_long", "formula": "any(cohort_month)"},
    "cohort_week": {"source": "gold.ua_cohort_long", "formula": "any(cohort_week)"},
    "cohort_day": {"source": "computed", "formula": "arrayJoin(range(mature_cohort_day_max + 1))", "aggregation": "Row explosion: 1 row per day 0..N where N = min(days_since_install, 400)"},
    "platform": {"source": "gold.ua_cohort_long", "formula": "pass-through"},
    "application": {"source": "gold.ua_cohort_long", "formula": "pass-through"},
    "country": {"source": "gold.ua_cohort_long", "formula": "pass-through"},
    "media_source": {"source": "gold.ua_cohort_long", "formula": "pass-through"},
    "promo_campaign": {"source": "gold.ua_cohort_long", "formula": "pass-through"},
    "promo_campaign_id": {"source": "gold.ua_cohort_long", "formula": "pass-through"},
    "ad": {"source": "gold.ua_cohort_long", "formula": "pass-through"},
    "adset": {"source": "gold.ua_cohort_long", "formula": "pass-through"},
    "installs": {"source": "gold.ua_cohort_long", "formula": "sumIf(installs, day_idx=0)", "aggregation": "Day-0 install count only"},
    "spend": {"source": "gold.ua_cohort_long", "formula": "sumIf(cost, day_idx=0)", "aggregation": "Day-0 cost only"},
    "ad_revenue_gross": {"source": "gold.ua_cohort_long", "formula": "ad_values[indexOf(ad_days, cohort_day)]", "aggregation": "Point-in-time from sumMap array"},
    "ad_revenue_gross_cumulative": {"source": "gold.ua_cohort_long", "formula": "ad_cumulative_values[arrayLastIndex(x -> x <= cohort_day, ad_days)]", "aggregation": "arrayCumSum running total"},
    "ad_revenue_gross_prev_day": {"source": "gold.ua_cohort_long", "formula": "ad_cumulative_values[arrayLastIndex(x -> x < cohort_day, ad_days)]"},
    "ad_revenue_gross_day0": {"source": "gold.ua_cohort_long", "formula": "ad_values[indexOf(ad_days, 0)]"},
    "total_revenue_net": {"source": "gold.ua_cohort_long", "formula": "total_values[indexOf(total_days, cohort_day)]", "aggregation": "Point-in-time from sumMap array"},
    "total_revenue_net_cumulative": {"source": "gold.ua_cohort_long", "formula": "total_cumulative_values[arrayLastIndex(x -> x <= cohort_day, total_days)]", "aggregation": "arrayCumSum running total"},
    "total_revenue_net_prev_day": {"source": "gold.ua_cohort_long", "formula": "total_cumulative_values[arrayLastIndex(x -> x < cohort_day, total_days)]"},
    "total_revenue_net_day0": {"source": "gold.ua_cohort_long", "formula": "total_values[indexOf(total_days, 0)]"},
    "version": {"source": "system", "formula": "now()"}
  },

  "gold.app_revenue_by_source_daily": {
    "_model": "gold__app_revenue_by_source_daily.sql",
    "_sources": ["silver__subscription_table", "silver__inapp_table", "magify_payments_events", "silver__applovin_user_revenue_table", "silver__apple_revenue_table", "silver__adjust_revenue_table", "silver__applovin_impression_revenue_table"],
    "_join_strategy": "7 source CTEs processed independently (no joins), combined via UNION ALL. Each CTE applies platform normalization and revenue conversion. Filtered to 30-app allowlist.",
    "event_date": {"source": "all 7 sources", "formula": "toDate(toTimeZone(event_time, 'America/Los_Angeles')) or equivalent per source"},
    "app_name": {"source": "all 7 sources", "formula": "coalesce(nullIf(app_name, ''), 'unknown')"},
    "platform": {"source": "all 7 sources", "formula": "multiIf(platform LIKE '%ios%', 'ios', LIKE '%and%', 'android', 'unknown')"},
    "source_tag": {"source": "literal", "formula": "Constant per CTE: 'appsyoulove', 'magify', 'apple', 'adjust', 'applovin'"},
    "source_model": {"source": "literal", "formula": "Constant naming the silver source table"},
    "ad_revenue_gross": {"source": "silver.applovin_* tables", "formula": "sum(ad_revenue_gross_usd)", "aggregation": "SUM. 0 for non-ad sources."},
    "inapp_revenue_gross": {"source": "silver.inapp_table / magify_payments_events", "formula": "sum(signed local_price / currency_rates_denominator)", "aggregation": "SUM. Refunds negated."},
    "subs_revenue_gross": {"source": "silver.subscription_table", "formula": "sum(signed local_price / currency_rates_denominator)", "aggregation": "SUM. Cancellations negated."},
    "purchase_events_count": {"source": "silver.inapp_table / silver.subscription_table", "formula": "countIf(event_name='purchase')", "aggregation": "COUNT"},
    "refund_events_count": {"source": "silver.inapp_table / silver.subscription_table", "formula": "countIf(event_name='refund') or countIf(type='CANCELLATION')", "aggregation": "COUNT"},
    "impressions_count": {"source": "silver.applovin_* / silver.adjust_revenue_table", "formula": "sum(impressions_count)", "aggregation": "SUM. 0 for payment sources."},
    "rows_count": {"source": "all sources", "formula": "count() or sum(rows_count)", "aggregation": "COUNT/SUM depending on source"}
  },

  "gold.ua_cohort_wide": {
    "_model": "gold__ua_cohort_wide.sql",
    "_sources": ["gold__ua_cohort_long", "gold__ua_payers", "gold__ua_cohort_activity_utn"],
    "_join_strategy": "Main CTE from gold.ua_cohort_long pivoted into day-bucket columns (d0/1/2/3/7/14/30/180/360) via sumIf. LEFT JOIN to gold.ua_payers for payer bucket metrics. LEFT JOIN to gold.ua_cohort_activity_utn for active_users_utn. All joins on 9-column dimension key."
  }
}
